landregistry/enhanced_logging/__init__.py
landregistry/enhanced_logging/enhanced_logging.py
landregistry/enhanced_logging/filters.py
landregistry/enhanced_logging/flask_enhanced_logging.py
landregistry/enhanced_logging/formatters.py
landregistry/enhanced_logging/kombu_enhanced_logging.py
landregistry/enhanced_logging/py.typed
landregistry/enhanced_logging/stubs/__init__.py
landregistry/enhanced_logging/stubs/exceptions.py
landregistry/enhanced_logging/stubs/flask.py
landregistry/enhanced_logging/stubs/kombu.py
landregistry_enhanced_logging-2.0.3.dist-info/METADATA
landregistry_enhanced_logging-2.0.3.dist-info/WHEEL
landregistry_enhanced_logging-2.0.3.dist-info/top_level.txt
landregistry_enhanced_logging-2.0.3.dist-info/RECORD
