Metadata-Version: 2.1
Name: landregistry-enhanced-logging
Version: 2.0.3
Summary: Standardised logging configuration for HMLR applications
Author: Ian Harvey
Author-email: ian.harvey@landregistry.gov.uk
License: MIT
Requires-Python: >=3.9
Provides-Extra: flask
Requires-Dist: flask >=2.2.0 ; extra == 'flask'
Requires-Dist: landregistry-trace-id >=1.0.0 ; extra == 'flask'
Provides-Extra: kombu
Requires-Dist: kombu >=5.0.0 ; extra == 'kombu'
